qablet_basic-0.4.5.dist-info/METADATA
qablet_basic-0.4.5.dist-info/WHEEL
qablet/base/flags.py
qablet/base/mc.py
qablet/base/base.py
qablet/base/utils.py
qablet/base/cf.py
qablet/base/__init__.py
qablet/base/fixed.py
qablet/hullwhite/fd.py
qablet/black_scholes/fd.py
qablet/black_scholes/__init__.py
qablet/local_vol/mc.py
qablet/_qablet.cpython-311-aarch64-linux-gnu.so
qablet_basic-0.4.5.dist-info/RECORD
