Metadata-Version: 2.3
Name: qablet_basic
Version: 0.4.5
Summary: A suite of basic models to price qablet contracts. See Project links for details.
Project-URL: Documentation, https://qablet-academy.github.io/intro/
